hugging_py_face/__about__.py
hugging_py_face/__init__.py
hugging_py_face/audio_processing.py
hugging_py_face/base_api.py
hugging_py_face/computer_vision.py
hugging_py_face/config_parser.py
hugging_py_face/exceptions.py
hugging_py_face/multimedia_processing.py
hugging_py_face/nlp.py
hugging_py_face/config/config.yaml
hugging_py_face/config/logging.yaml
hugging_py_face-0.5.3.dist-info/LICENSE.txt
hugging_py_face-0.5.3.dist-info/METADATA
hugging_py_face-0.5.3.dist-info/WHEEL
hugging_py_face-0.5.3.dist-info/top_level.txt
hugging_py_face-0.5.3.dist-info/RECORD
