Metadata-Version: 2.1
Name: hugging-py-face
Version: 0.5.3
Summary: Hugging-Py-Face, the Python client for the Hugging Face Inference API.
Home-page: https://github.com/MinuraPunchihewa/hugging_py_face
Author: Minura Punchihewa
Author-email: minurapunchihewa17@gmail.com
License: GPL-3.0
Download-URL: https://pypi.org/project/hugging-py-face/
Platform: UNKNOWN
Classifier: Programming Language :: Python :: 3
Classifier: License :: OSI Approved :: GNU General Public License v3 (GPLv3)
Classifier: Operating System :: OS Independent
Requires-Python: >=3.7
Requires-Dist: requests
Requires-Dist: pyyaml
Requires-Dist: pandas
Requires-Dist: python-dotenv
Requires-Dist: huggingface-hub
